{
"boxs":[
   {
    "description":"Lorem ipsum dolor sit amet, consec tetur adipiscing elit, sed do eiusmod tempor incididunt ut labore.",
    "title":"Shoo Phar Mhan",
    "userTitle":"Kang Masak"
   },

   {
    "description":"Lorem ipsum dolor sit amet, consec tetur adipiscing elit, sed do eiusmod tempor incididunt ut labore.",
    "title":"Shoo Phar Dhie",
    "userTitle":"Kang Bakso"
   },
   {
    "description":"Lorem ipsum dolor sit amet, consec tetur adipiscing elit, sed do eiusmod tempor incididunt ut labore.",
    "title":"Shoo Yha Thi",
    "userTitle":"Kang Ngomel"
   },
   {
    "description":"Lorem ipsum dolor sit amet, consec tetur adipiscing elit, sed do eiusmod tempor incididunt ut labore.",
    "title":"Shoo Mhar Nhi",
    "userTitle":"Kang Gombat"
   }

]

}